natcap/__init__.pxd
natcap/invest/__init__.py
natcap/invest/__main__.py
natcap/invest/annual_water_yield.py
natcap/invest/carbon.py
natcap/invest/cli.py
natcap/invest/coastal_vulnerability.py
natcap/invest/crop_production_percentile.py
natcap/invest/crop_production_regression.py
natcap/invest/datastack.py
natcap/invest/file_registry.py
natcap/invest/forest_carbon_edge_effect.py
natcap/invest/habitat_quality.py
natcap/invest/hra.py
natcap/invest/models.py
natcap/invest/pollination.py
natcap/invest/routedem.py
natcap/invest/scenario_gen_proximity.py
natcap/invest/spec.py
natcap/invest/stormwater.py
natcap/invest/ui_server.py
natcap/invest/unit_definitions.txt
natcap/invest/unit_registry.py
natcap/invest/urban_cooling_model.py
natcap/invest/urban_flood_risk_mitigation.py
natcap/invest/urban_nature_access.py
natcap/invest/usage.py
natcap/invest/utils.py
natcap/invest/validation.py
natcap/invest/validation_messages.py
natcap/invest/wave_energy.py
natcap/invest/wind_energy.py
natcap/invest/coastal_blue_carbon/__init__.py
natcap/invest/coastal_blue_carbon/coastal_blue_carbon.py
natcap/invest/coastal_blue_carbon/preprocessor.py
natcap/invest/delineateit/__init__.py
natcap/invest/delineateit/delineateit.py
natcap/invest/delineateit/delineateit_core.cpp
natcap/invest/delineateit/delineateit_core.cpython-311-x86_64-linux-gnu.so
natcap/invest/delineateit/delineateit_core.pyx
natcap/invest/internationalization/README.md
natcap/invest/internationalization/messages.pot
natcap/invest/internationalization/locales/es/LC_MESSAGES/messages.mo
natcap/invest/internationalization/locales/es/LC_MESSAGES/messages.po
natcap/invest/internationalization/locales/zh/LC_MESSAGES/messages.mo
natcap/invest/internationalization/locales/zh/LC_MESSAGES/messages.po
natcap/invest/managed_raster/LRUCache.h
natcap/invest/managed_raster/ManagedRaster.h
natcap/invest/managed_raster/__init__.py
natcap/invest/managed_raster/managed_raster.pxd
natcap_invest-3.17.1.dist-info/METADATA
natcap_invest-3.17.1.dist-info/WHEEL
natcap_invest-3.17.1.dist-info/entry_points.txt
natcap_invest-3.17.1.dist-info/top_level.txt
natcap_invest-3.17.1.dist-info/RECORD
natcap_invest-3.17.1.dist-info/licenses/LICENSE.txt
