Metadata-Version: 2.4
Name: natcap.invest
Version: 3.17.1
Summary: InVEST Ecosystem Service models
Maintainer: Natural Capital Project Software Team
License-Expression: Apache-2.0
Project-URL: homepage, http://github.com/natcap/invest
Keywords: gis,invest,ecosystem services
Classifier: Intended Audience :: Developers
Classifier: Development Status :: 5 - Production/Stable
Classifier: Intended Audience :: Science/Research
Classifier: Natural Language :: English
Classifier: Operating System :: MacOS :: MacOS X
Classifier: Operating System :: Microsoft
Classifier: Operating System :: POSIX
Classifier: Programming Language :: Python :: 3
Classifier: Programming Language :: Python :: 3.9
Classifier: Programming Language :: Python :: 3.10
Classifier: Programming Language :: Python :: 3.11
Classifier: Programming Language :: Python :: 3.12
Classifier: Programming Language :: Python :: 3.13
Classifier: Programming Language :: Cython
Classifier: Topic :: Scientific/Engineering :: GIS
Requires-Python: >=3.9
License-File: LICENSE.txt
Requires-Dist: gdal>=3.4.2
Requires-Dist: pyro5
Requires-Dist: pandas>=1.2.1
Requires-Dist: numpy!=1.16.0,>=1.11.0
Requires-Dist: rtree!=0.9.1,>=0.8.2
Requires-Dist: shapely>=2.0.0
Requires-Dist: scipy!=1.12.*,>=1.9.0
Requires-Dist: pygeoprocessing>=2.4.6
Requires-Dist: taskgraph>=0.11.0
Requires-Dist: psutil>=5.6.6
Requires-Dist: chardet>=3.0.4
Requires-Dist: pint
Requires-Dist: babel
Requires-Dist: flask
Requires-Dist: flask_cors
Requires-Dist: requests
Requires-Dist: geometamaker>=0.2.0
Requires-Dist: pydantic
Requires-Dist: certifi
Dynamic: license-file
Dynamic: requires-dist
